setup.py
latimes_pluggablemaps_uscounties.egg-info/PKG-INFO
latimes_pluggablemaps_uscounties.egg-info/SOURCES.txt
latimes_pluggablemaps_uscounties.egg-info/dependency_links.txt
latimes_pluggablemaps_uscounties.egg-info/top_level.txt
us_counties/__init__.py
us_counties/admin.py
us_counties/generic_views.py
us_counties/load.py
us_counties/models.py
us_counties/tests.py
us_counties/urls.py
us_counties/views.py
us_counties/data/fips.csv
us_counties/management/__init__.py
us_counties/management/commands/__init__.py
us_counties/management/commands/loaduscounties.py
us_counties/templates/base.html
us_counties/templates/county_list.json
us_counties/templates/openlayers.html
us_counties/templates/openlayers.js
us_counties/templates/polymaps.html
us_counties/templates/polymaps.js