Metadata-Version: 1.0
Name: latimes-pluggablemaps-uscounties
Version: alpha-0.12
Summary: L.A. Times Pluggable Maps: U.S. Counties
Home-page: http://github.com/datadesk/latimes-pluggablemaps-uscounties
Author: Ben Welsh
Author-email: ben.welsh@gmail.com
License: MIT
Download-URL: http://github.com/datadesk/latimes-pluggablemaps-uscounties.git
Keywords: gis geographical maps earth usa counties boundaries
Platform: UNKNOWN
Classifier: Development Status :: 3 - Alpha
Classifier: Intended Audience :: Developers
Classifier: Intended Audience :: Science/Research
Classifier: License :: OSI Approved :: MIT License
Classifier: Operating System :: OS Independent
Classifier: Programming Language :: Python
Classifier: Topic :: Scientific/Engineering :: GIS
Classifier: Topic :: Software Development :: Libraries :: Python Modules
